sphinx_ansible_ext/__init__.py
sphinx_ansible_ext/conversions.py
sphinx_ansible_ext/directives.py
proxops-0.2.0.dist-info/LICENSE
proxops-0.2.0.dist-info/METADATA
proxops-0.2.0.dist-info/WHEEL
proxops-0.2.0.dist-info/top_level.txt
proxops-0.2.0.dist-info/zip-safe
proxops-0.2.0.dist-info/RECORD
